{
  "autorun": false,
  "autoKill": true,
  "terminals": [
    {
      "name": "ibcscharts",
      "cwd": "../../ibcscharts",
      "open": true,
      "onlyMultiple": true,
      "command": "npm run dev"
    },
    {
      "name": "IRChartsPowerbi",
      "cwd": "../../IRChartsPowerbi",
      "open": true,
      "onlyMultiple": true,
      "command": "npm run start:next"
    },
    {
      "name": "git push origin all",
      "commands": [
        "git -C ../../ibcscharts push origin --all",
        "git -C ../../IRChartsPowerbi push origin --all",
        "exit"
      ],
      "onlySingle": true,
      "open": true
    },
    {
      "name": "git pull upstream development",
      "commands": [
        "git -C ../../ibcscharts pull upstream development",
        "git -C ../../IRChartsPowerbi pull upstream development",
        "exit"
      ],
      "onlySingle": true,
      "open": true
    },
    {
      "name": "git pull origin development",
      "commands": [
        "git -C ../../ibcscharts pull origin development",
        "git -C ../../IRChartsPowerbi pull origin development",
        "exit"
      ],
      "onlySingle": true,
      "open": true
    },
    {
      "name": "git pull upstream matrix-refactor",
      "commands": [
        "git -C ../../ibcscharts pull upstream matrix-refactor",
        "git -C ../../IRChartsPowerbi pull upstream matrix-refactor",
        "exit"
      ],
      "onlySingle": true,
      "open": true
    },
    {
      "name": "git pull origin matrix-refactor",
      "commands": [
        "git -C ../../ibcscharts pull origin matrix-refactor",
        "git -C ../../IRChartsPowerbi pull origin matrix-refactor",
        "exit"
      ],
      "onlySingle": true,
      "open": true
    },
    {
      "name": "git pull akila matrix-refactor-iteration-2",
      "commands": [
        "git -C ../../ibcscharts pull akila matrix-refactor-iteration-2",
        "git -C ../../IRChartsPowerbi pull akila matrix-refactor-iteration-2",
        "exit"
      ],
      "onlySingle": true,
      "open": true
    },
    {
      "name": "git pull mani matrix-refactor",
      "commands": [
        "git -C ../../ibcscharts pull mani matrix-refactor",
        "git -C ../../IRChartsPowerbi pull mani matrix-refactor",
        "exit"
      ],
      "onlySingle": true,
      "open": true
    },
    {
      "name": "git checkout development",
      "commands": [
        "git -C ../../ibcscharts checkout development",
        "git -C ../../IRChartsPowerbi checkout development",
        "exit"
      ],
      "onlySingle": true,
      "open": true
    },
    {
      "name": "git checkout matrix-refactor",
      "commands": [
        "git -C ../../ibcscharts checkout matrix-refactor",
        "git -C ../../IRChartsPowerbi checkout matrix-refactor",
        "exit"
      ],
      "onlySingle": true,
      "open": true
    },
    {
      "name": "npm install",
      "commands": [
        "npm ci --prefix ../../ibcscharts -OR npm install --prefix ../../ibcscharts",
        "npm ci --prefix ../../IRChartsPowerbi -OR npm install --prefix ../../IRChartsPowerbi",
        "exit"
      ],
      "onlySingle": true,
      "open": true
    }
  ]
}
